gupy/__init__.py
gupy-0.0.1.dist-info/LICENSE
gupy-0.0.1.dist-info/WHEEL
gupy-0.0.1.dist-info/METADATA
gupy-0.0.1.dist-info/RECORD
